diswebhookutils/__init__.py
diswebhookutils-0.0.1.dist-info/LICENSE
diswebhookutils-0.0.1.dist-info/METADATA
diswebhookutils-0.0.1.dist-info/WHEEL
diswebhookutils-0.0.1.dist-info/top_level.txt
diswebhookutils-0.0.1.dist-info/RECORD
